documentocr_verdict/__init__.py
documentocr_verdict/ocr.py
documentocr_verdict-1.0.0.dist-info/LICENSE
documentocr_verdict-1.0.0.dist-info/METADATA
documentocr_verdict-1.0.0.dist-info/WHEEL
documentocr_verdict-1.0.0.dist-info/top_level.txt
documentocr_verdict-1.0.0.dist-info/RECORD
