Metadata-Version: 2.1
Name: documentocr_verdict
Version: 1.0.0
Summary: This repository contains a Python program designed to execute Optical Character Recognition (OCR)
Home-page: 
Author: Amaan Patel
Author-email: amaan@codeverdict.ai
Classifier: Programming Language :: Python :: 3
Classifier: License :: OSI Approved :: MIT License
Classifier: Operating System :: OS Independent
Requires-Python: >=3.7
License-File: LICENSE
Requires-Dist: google-cloud-vision
Requires-Dist: opencv-python-headless
Requires-Dist: numpy
Requires-Dist: google-auth
Requires-Dist: PyMuPDF
